verdi_llm/__init__.py
verdi_llm/__main__.py
verdi_llm/cli/__init__.py
verdi_llm/cli/cmd_llm.py
verdi_llm/cli/generate_verdi_cli_json.py
verdi_llm/cli/llm_backend.py
verdi_llm/cli/verdi_cli.json
verdi_llm/cli/verdi_llm_shell.py
verdi_llm-0.1.3.dist-info/entry_points.txt
verdi_llm-0.1.3.dist-info/licenses/LICENSE.txt
verdi_llm-0.1.3.dist-info/WHEEL
verdi_llm-0.1.3.dist-info/METADATA
verdi_llm-0.1.3.dist-info/RECORD
